Metadata-Version: 2.1
Name: scReadSim
Version: 1.4.1
Summary: A single-cell RNA-seq and ATAC-seq read simulator.
Home-page: https://github.com/JSB-UCLA/scReadSim
Author: Guanao Yan
Author-email: gayan@g.ucla.com
Classifier: Programming Language :: Python :: 3
Classifier: License :: OSI Approved :: MIT License
Classifier: Operating System :: OS Independent
Requires-Python: >=3.6
License-File: LICENSE
Requires-Dist: numpy
Requires-Dist: pandas
Requires-Dist: pysam
Requires-Dist: tqdm
Requires-Dist: joblib
Requires-Dist: pathlib
Requires-Dist: Bio
Requires-Dist: gffpandas
Requires-Dist: rpy2
